rechat_eval/__init__.py
rechat_eval/_modidx.py
rechat_eval/airtable.py
rechat_eval/smith.py
rechat_eval-0.0.3.dist-info/LICENSE
rechat_eval-0.0.3.dist-info/METADATA
rechat_eval-0.0.3.dist-info/WHEEL
rechat_eval-0.0.3.dist-info/entry_points.txt
rechat_eval-0.0.3.dist-info/top_level.txt
rechat_eval-0.0.3.dist-info/RECORD
