Metadata-Version: 2.1
Name: rechat-eval
Version: 0.0.3
Summary: Tools for Evaluating Rechat LLMs
Home-page: https://github.com/parlance-labs/rechat-eval
Author: Hamel Husain
Author-email: hamel.husain@gmail.com
License: Apache Software License 2.0
Keywords: nbdev jupyter notebook python
Classifier: Development Status :: 4 - Beta
Classifier: Intended Audience :: Developers
Classifier: Natural Language :: English
Classifier: Programming Language :: Python :: 3.9
Classifier: Programming Language :: Python :: 3.10
Classifier: License :: OSI Approved :: Apache Software License
Requires-Python: >=3.9
License-File: LICENSE
Requires-Dist: pyairtable
Requires-Dist: langfree >=0.0.29
Provides-Extra: dev
